[{"date": "2018-07-10", "open": 228.0, "high": 228.87, "low": 225.8486, "close": 226.85, "ticker": "GS"}, {"date": "2018-07-11", "open": 225.76, "high": 227.25, "low": 225.2, "close": 225.66, "ticker": "GS"}, {"date": "2018-07-12", "open": 227.64, "high": 227.8, "low": 225.7701, "close": 227.22, "ticker": "GS"}, {"date": "2018-07-13", "open": 226.63, "high": 228.62, "low": 223.93, "close": 226.41, "ticker": "GS"}, {"date": "2018-07-16", "open": 227.2, "high": 231.44, "low": 226.74, "close": 231.44, "ticker": "GS"}, {"date": "2018-07-17", "open": 231.48, "high": 233.23, "low": 226.87, "close": 231.02, "ticker": "GS"}, {"date": "2018-07-18", "open": 232.34, "high": 233.72, "low": 230.15, "close": 231.24, "ticker": "GS"}, {"date": "2018-07-19", "open": 231.11, "high": 231.99, "low": 228.98, "close": 229.63, "ticker": "GS"}, {"date": "2018-07-20", "open": 229.01, "high": 232.05, "low": 228.8, "close": 231.69, "ticker": "GS"}, {"date": "2018-07-23", "open": 231.8, "high": 234.86, "low": 231.72, "close": 233.76, "ticker": "GS"}, {"date": "2018-07-24", "open": 234.75, "high": 237.48, "low": 234.34, "close": 235.88, "ticker": "GS"}, {"date": "2018-07-25", "open": 235.01, "high": 236.85, "low": 233.95, "close": 236.69, "ticker": "GS"}, {"date": "2018-07-26", "open": 237.0, "high": 238.335, "low": 236.43, "close": 237.11, "ticker": "GS"}, {"date": "2018-07-27", "open": 237.96, "high": 238.8, "low": 235.99, "close": 237.64, "ticker": "GS"}, {"date": "2018-07-30", "open": 238.0, "high": 239.73, "low": 236.89, "close": 238.95, "ticker": "GS"}, {"date": "2018-07-31", "open": 239.5, "high": 239.5, "low": 236.55, "close": 237.43, "ticker": "GS"}, {"date": "2018-08-01", "open": 238.5, "high": 239.4, "low": 235.78, "close": 236.04, "ticker": "GS"}, {"date": "2018-08-02", "open": 233.93, "high": 235.21, "low": 232.77, "close": 233.99, "ticker": "GS"}, {"date": "2018-08-03", "open": 234.44, "high": 235.52, "low": 233.49, "close": 234.09, "ticker": "GS"}, {"date": "2018-08-06", "open": 234.14, "high": 236.98, "low": 234.03, "close": 235.93, "ticker": "GS"}, {"date": "2018-08-07", "open": 237.25, "high": 239.46, "low": 236.49, "close": 237.83, "ticker": "GS"}, {"date": "2018-08-08", "open": 238.12, "high": 239.16, "low": 236.23, "close": 236.37, "ticker": "GS"}, {"date": "2018-08-09", "open": 236.35, "high": 236.845, "low": 233.39, "close": 233.78, "ticker": "GS"}, {"date": "2018-08-10", "open": 230.97, "high": 231.455, "low": 228.11, "close": 229.61, "ticker": "GS"}]