{"symbol": "AMD", "companyName": "Advanced Micro Devices Inc.", "primaryExchange": "NASDAQ Capital Market", "sector": "Technology", "calculationPrice": "close", "open": 19.08, "openTime": 1533907800233, "close": 19.06, "closeTime": 1533931200315, "high": 19.48, "low": 18.85, "latestPrice": 19.06, "latestSource": "Close", "latestTime": "August 10, 2018", "latestUpdate": 1533931200315, "latestVolume": 65666519, "iexRealtimePrice": null, "iexRealtimeSize": null, "iexLastUpdated": null, "delayedPrice": 19.06, "delayedPriceTime": 1533931200315, "extendedPrice": 19.02, "extendedChange": -0.04, "extendedChangePercent": -0.0021, "extendedPriceTime": 1533934764700, "previousClose": 19.1, "change": -0.04, "changePercent": -0.00209, "iexMarketPercent": null, "iexVolume": null, "avgTotalVolume": 67268434, "iexBidPrice": null, "iexBidSize": null, "iexAskPrice": null, "iexAskSize": null, "marketCap": 18581068116, "peRatio": 56.06, "week52High": 20.18, "week52Low": 9.04, "ytdChange": 0.7337934244080143}