[{"date": "2018-07-11", "open": 340.0497, "high": 342.6966, "low": 337.5222, "close": 338.9253, "ticker": "BA"}, {"date": "2018-07-12", "open": 343.5823, "high": 344.8958, "low": 341.0522, "close": 344.3286, "ticker": "BA"}, {"date": "2018-07-13", "open": 345.2938, "high": 349.513, "low": 344.4977, "close": 349.0652, "ticker": "BA"}, {"date": "2018-07-16", "open": 352.2295, "high": 354.5879, "low": 350.6175, "close": 354.3491, "ticker": "BA"}, {"date": "2018-07-17", "open": 355.8516, "high": 357.2348, "low": 353.2943, "close": 355.1252, "ticker": "BA"}, {"date": "2018-07-18", "open": 357.2348, "high": 360.0807, "low": 352.5219, "close": 358.4587, "ticker": "BA"}, {"date": "2018-07-19", "open": 355.9312, "high": 357.6229, "low": 353.5132, "close": 353.5828, "ticker": "BA"}, {"date": "2018-07-20", "open": 351.3041, "high": 355.2347, "low": 351.2643, "close": 353.155, "ticker": "BA"}, {"date": "2018-07-23", "open": 353.2545, "high": 353.2545, "low": 350.6573, "close": 351.533, "ticker": "BA"}, {"date": "2018-07-24", "open": 354.9959, "high": 357.7025, "low": 352.8962, "close": 356.5084, "ticker": "BA"}, {"date": "2018-07-25", "open": 349.7916, "high": 354.5481, "low": 343.8012, "close": 354.1699, "ticker": "BA"}, {"date": "2018-07-26", "open": 353.6326, "high": 358.4289, "low": 353.5231, "close": 357.5532, "ticker": "BA"}, {"date": "2018-07-27", "open": 359.2847, "high": 362.7476, "low": 357.7065, "close": 358.8767, "ticker": "BA"}, {"date": "2018-07-30", "open": 360.2101, "high": 360.6678, "low": 348.7467, "close": 349.3338, "ticker": "BA"}, {"date": "2018-07-31", "open": 352.6375, "high": 357.2572, "low": 352.3191, "close": 354.5481, "ticker": "BA"}, {"date": "2018-08-01", "open": 352.3489, "high": 356.1505, "low": 348.7766, "close": 351.0255, "ticker": "BA"}, {"date": "2018-08-02", "open": 346.9058, "high": 349.0055, "low": 344.3286, "close": 348.0104, "ticker": "BA"}, {"date": "2018-08-03", "open": 347.7815, "high": 349.2642, "low": 343.9703, "close": 346.7267, "ticker": "BA"}, {"date": "2018-08-06", "open": 345.662, "high": 345.662, "low": 341.4329, "close": 344.8659, "ticker": "BA"}, {"date": "2018-08-07", "open": 346.3386, "high": 350.3886, "low": 343.8012, "close": 349.0353, "ticker": "BA"}, {"date": "2018-08-08", "open": 348.7766, "high": 349.8911, "low": 344.5475, "close": 346.07, "ticker": "BA"}, {"date": "2018-08-09", "open": 346.07, "high": 346.84, "low": 343.12, "close": 343.72, "ticker": "BA"}, {"date": "2018-08-10", "open": 341.0, "high": 341.0, "low": 336.45, "close": 339.41, "ticker": "BA"}]