{"symbol": "C", "companyName": "Citigroup Inc.", "primaryExchange": "New York Stock Exchange", "sector": "Financial Services", "calculationPrice": "close", "open": 70.63, "openTime": 1533907829092, "close": 70.26, "closeTime": 1533931360644, "high": 70.9, "low": 69.9, "latestPrice": 70.26, "latestSource": "Close", "latestTime": "August 10, 2018", "latestUpdate": 1533931360644, "latestVolume": 20217732, "iexRealtimePrice": null, "iexRealtimeSize": null, "iexLastUpdated": null, "delayedPrice": 70.26, "delayedPriceTime": 1533931360644, "extendedPrice": 70.12, "extendedChange": -0.14, "extendedChangePercent": -0.00199, "extendedPriceTime": 1533933303721, "previousClose": 71.98, "change": -1.72, "changePercent": -0.0239, "iexMarketPercent": null, "iexVolume": null, "avgTotalVolume": 15702324, "iexBidPrice": null, "iexBidSize": null, "iexAskPrice": null, "iexAskSize": null, "marketCap": 176816696247, "peRatio": 11.71, "week52High": 80.7, "week52Low": 64.38, "ytdChange": -0.06470601782959481}